{"assets/images/budgetbuddy_intro.png":["assets/images/budgetbuddy_intro.png"],"assets/images/portfolio_image.png":["assets/images/portfolio_image.png"],"assets/images/socialease_intro.png":["assets/images/socialease_intro.png"],"assets/logos/dartlang-icon.svg":["assets/logos/dartlang-icon.svg"],"assets/logos/dotnet-icon.svg":["assets/logos/dotnet-icon.svg"],"assets/logos/firebase-icon.svg":["assets/logos/firebase-icon.svg"],"assets/logos/flutterio-icon.svg":["assets/logos/flutterio-icon.svg"],"assets/logos/os-ios-svgrepo-com.svg":["assets/logos/os-ios-svgrepo-com.svg"],"assets/logos/sql-icon.svg":["assets/logos/sql-icon.svg"],"assets/logos/swift-icon.svg":["assets/logos/swift-icon.svg"],"assets/logos/xcode-svgrepo-com.svg":["assets/logos/xcode-svgrepo-com.svg"],"assets/lotties/home_astronaut.json":["assets/lotties/home_astronaut.json"],"assets/pdf/Jakub Trznadel - Mobile Developer - Resume.pdf":["assets/pdf/Jakub Trznadel - Mobile Developer - Resume.pdf"],"packages/cupertino_icons/assets/CupertinoIcons.ttf":["packages/cupertino_icons/assets/CupertinoIcons.ttf"],"packages/font_awesome_flutter/lib/fonts/fa-brands-400.ttf":["packages/font_awesome_flutter/lib/fonts/fa-brands-400.ttf"],"packages/font_awesome_flutter/lib/fonts/fa-regular-400.ttf":["packages/font_awesome_flutter/lib/fonts/fa-regular-400.ttf"],"packages/font_awesome_flutter/lib/fonts/fa-solid-900.ttf":["packages/font_awesome_flutter/lib/fonts/fa-solid-900.ttf"]}